LICENSE
MANIFEST.in
README.md
setup.cfg
setup.py
custom_url/__init__.py
custom_url/admin.py
custom_url/apps.py
custom_url/forms.py
custom_url/models.py
custom_url/views.py
custom_url/management/__init__.py
custom_url/management/commands/__init__.py
custom_url/management/commands/update_urls.py
custom_url/mediafiles/custom_url/index.html
custom_url/mediafiles/custom_url/index_3COu6Cg.html
custom_url/mediafiles/custom_url/index_7bZByR5.html
custom_url/mediafiles/custom_url/index_Ib7JKJ2.html
custom_url/mediafiles/custom_url/index_OVSCQxZ.html
custom_url/mediafiles/custom_url/index_TZ2POmd.html
custom_url/mediafiles/custom_url/index_ViRQUv1.html
custom_url/mediafiles/custom_url/index_XsogYJQ.html
custom_url/mediafiles/custom_url/index_Yjxv7sc.html
custom_url/mediafiles/custom_url/index_bY7mfll.html
custom_url/mediafiles/custom_url/index_nlTgaXx.html
custom_url/mediafiles/custom_url/index_ogEPft4.html
custom_url/mediafiles/custom_url/index_rqYkVby.html
custom_url/mediafiles/custom_url/index_rqj5U8O.html
custom_url/mediafiles/custom_url/index_wheS0Ww.html
custom_url/mediafiles/custom_url/my_file.txt
custom_url/mediafiles/custom_url/my_file_01SVJDs.txt
custom_url/mediafiles/custom_url/my_file_0BJ4Ph1.txt
custom_url/mediafiles/custom_url/my_file_2BlHoiZ.txt
custom_url/mediafiles/custom_url/my_file_2z3vpbQ.txt
custom_url/mediafiles/custom_url/my_file_3mZrvt6.txt
custom_url/mediafiles/custom_url/my_file_4AgrNf5.txt
custom_url/mediafiles/custom_url/my_file_5Aztcp9.txt
custom_url/mediafiles/custom_url/my_file_5En1MkK.txt
custom_url/mediafiles/custom_url/my_file_7P7bOOF.txt
custom_url/mediafiles/custom_url/my_file_7bz7Sxl.txt
custom_url/mediafiles/custom_url/my_file_7iNWdzO.txt
custom_url/mediafiles/custom_url/my_file_9E9AydE.txt
custom_url/mediafiles/custom_url/my_file_9eQWWNo.txt
custom_url/mediafiles/custom_url/my_file_9mWY1lx.txt
custom_url/mediafiles/custom_url/my_file_AQcZzU0.txt
custom_url/mediafiles/custom_url/my_file_AVVN74v.txt
django_custom_url.egg-info/PKG-INFO
django_custom_url.egg-info/SOURCES.txt
django_custom_url.egg-info/dependency_links.txt
django_custom_url.egg-info/requires.txt
django_custom_url.egg-info/top_level.txt