Metadata-Version: 2.1
Name: django-custom-url
Version: 0.3
Summary: A Django app to easily manage custom url linked to static files.
Home-page: https://github.com/luciano-im/django-custom-url
Author: Luciano Muñoz
Author-email: hola@luciano.im
License: MIT
Project-URL: Documentation, https://github.com/luciano-im/django-custom-url#readme
Project-URL: Issues, https://github.com/luciano-im/django-custom-url/issues
Project-URL: Twitter, https://twitter.com/luciano_dev
Keywords: django,custom,url,path,file url,file path
Platform: UNKNOWN
Classifier: Environment :: Web Environment
Classifier: Framework :: Django :: 3.2
Classifier: Framework :: Django :: 4.0
Classifier: Intended Audience :: Developers
Classifier: License :: OSI Approved :: MIT License
Classifier: Natural Language :: English
Classifier: Operating System :: OS Independent
Classifier: Programming Language :: Python :: 3.8
Classifier: Programming Language :: Python :: 3.9
Classifier: Programming Language :: Python :: 3.10
Classifier: Topic :: Software Development :: Build Tools
License-File: LICENSE
